Metadata-Version: 1.0
Name: inspie
Version: 1.0
Summary: inspie
Home-page: UNKNOWN
Author: UNKNOWN
Author-email: UNKNOWN
License: UNKNOWN
Platform: UNKNOWN
